dateid.py
dateid-1.6.0.dist-info/METADATA
dateid-1.6.0.dist-info/WHEEL
dateid-1.6.0.dist-info/licenses/LICENSE.txt
dateid-1.6.0.dist-info/RECORD
