Metadata-Version: 2.4
Name: DateId
Version: 1.6.0
Summary: Calculate an integer value for months and dates from a base date.
License-Expression: MIT
License-File: LICENSE.txt
Author: Hendrik du Toit
Author-email: hendrik@brightedge.co.za
Maintainer: Hendrik du Toit
Maintainer-email: hendrikdt@citiqprepaid.co.za
Requires-Python: >=3.10
Classifier: Development Status :: 5 - Production/Stable
Classifier: Intended Audience :: Developers
Classifier: Intended Audience :: Information Technology
Classifier: Topic :: Software Development
Classifier: Topic :: Software Development :: Libraries
Classifier: License :: OSI Approved :: MIT License
Classifier: Programming Language :: Python :: 3.10
Classifier: Programming Language :: Python :: 3.11
Classifier: Programming Language :: Python :: 3.12
Classifier: Programming Language :: Python :: 3.13
Requires-Dist: beetools (>=5.2.4,<6.0.0)
Requires-Dist: displayfx (>=2.1.1,<3.0.0)
Requires-Dist: time-machine (>=3.2.0,<4.0.0)
Project-URL: Homepage, https://github.com/BrightEdgeeServices/DateId
Project-URL: Issues, https://github.com/BrightEdgeeServices/DateId/issues
Project-URL: Repository, https://github.com/BrightEdgeeServices/DateId.git
Project-URL: changelog, https://github.com/BrightEdgeeServices/DateId/releases
